onesignal/__init__.py
onesignal/api_client.py
onesignal/configuration.py
onesignal/exceptions.py
onesignal/model_utils.py
onesignal/rest.py
onesignal/api/__init__.py
onesignal/api/default_api.py
onesignal/apis/__init__.py
onesignal/model/__init__.py
onesignal/model/app.py
onesignal/model/apps.py
onesignal/model/basic_notification.py
onesignal/model/basic_notification_all_of.py
onesignal/model/basic_notification_all_of_android_background_layout.py
onesignal/model/begin_live_activity_request.py
onesignal/model/button.py
onesignal/model/buttons.py
onesignal/model/cancel_notification_success_response.py
onesignal/model/create_notification_success_response.py
onesignal/model/create_player_success_response.py
onesignal/model/create_segment_conflict_response.py
onesignal/model/create_segment_success_response.py
onesignal/model/create_subscription_request_body.py
onesignal/model/create_user_conflict_response.py
onesignal/model/create_user_conflict_response_errors_inner.py
onesignal/model/create_user_conflict_response_errors_items_meta.py
onesignal/model/delete_player_not_found_response.py
onesignal/model/delete_player_success_response.py
onesignal/model/delete_segment_not_found_response.py
onesignal/model/delete_segment_success_response.py
onesignal/model/delivery_data.py
onesignal/model/export_events_success_response.py
onesignal/model/export_players_request_body.py
onesignal/model/export_players_success_response.py
onesignal/model/filter.py
onesignal/model/filter_expressions.py
onesignal/model/generic_error.py
onesignal/model/generic_error_errors_inner.py
onesignal/model/get_notification_request_body.py
onesignal/model/identity_object.py
onesignal/model/inline_response200.py
onesignal/model/inline_response2003.py
onesignal/model/inline_response201.py
onesignal/model/inline_response202.py
onesignal/model/invalid_identifier_error.py
onesignal/model/no_subscribers_error.py
onesignal/model/notification.py
onesignal/model/notification200_errors.py
onesignal_python_api-2.2.1.dist-info/licenses/LICENSE
onesignal_python_api-2.2.1.dist-info/METADATA
onesignal_python_api-2.2.1.dist-info/WHEEL
onesignal_python_api-2.2.1.dist-info/top_level.txt
onesignal_python_api-2.2.1.dist-info/RECORD
