Metadata-Version: 2.4
Name: onesignal_python_api
Version: 2.2.1
Summary: OneSignal
Home-page: 
Author: OneSignal DevRel
Author-email: devrel@onesignal.com
Keywords: OpenAPI,OpenAPI-Generator,OneSignal
Requires-Python: >=3.6
License-File: LICENSE
Requires-Dist: urllib3>=1.25.3
Requires-Dist: python-dateutil
Dynamic: author
Dynamic: author-email
Dynamic: description
Dynamic: keywords
Dynamic: license-file
Dynamic: requires-dist
Dynamic: requires-python
Dynamic: summary
